RNApysoforms/__init__.py
RNApysoforms/calculate_exon_number.py
RNApysoforms/gene_filtering.py
RNApysoforms/make_plot.py
RNApysoforms/make_traces.py
RNApysoforms/read_ensembl_gtf.py
RNApysoforms/read_expression_matrix.py
RNApysoforms/shorten_gaps.py
RNApysoforms/to_intron.py
RNApysoforms/utils.py
rnapysoforms-1.2.12.dist-info/licenses/LICENSE
rnapysoforms-1.2.12.dist-info/METADATA
rnapysoforms-1.2.12.dist-info/WHEEL
rnapysoforms-1.2.12.dist-info/top_level.txt
rnapysoforms-1.2.12.dist-info/RECORD
