Metadata-Version: 2.4
Name: RNApysoforms
Version: 1.2.12
Summary: A Python package designed for visualizing RNA isoform structures and expression levels by leveraging Plotly for interactive plotting and Polars for efficient data manipulation, enabling the creation of fast-rendering, interactive plots.
Home-page: https://github.com/UK-SBCoA-EbbertLab/RNApysoforms
Author: Bernardo Aguzzoli Heberle
Author-email: Your Name <bernardo.aguzzoli@gmail.com>
License: MIT
Project-URL: Homepage, https://github.com/UK-SBCoA-EbbertLab/RNApysoforms
Keywords: plotly,RNA isoforms,transcripts,ggtranscript,bioinformatics,genomics
Classifier: License :: OSI Approved :: MIT License
Classifier: Programming Language :: Python
Classifier: Programming Language :: Python :: 3
Requires-Python: >=3.8
License-File: LICENSE
Requires-Dist: plotly>=5.0
Requires-Dist: polars[excel]<2.0,>=1.0
Requires-Dist: pyarrow<18.0,>=17.0
Requires-Dist: pandas<3.0,>=1.3
Dynamic: author
Dynamic: home-page
Dynamic: license-file
Dynamic: requires-python
